dpd_client/__init__.py
dpd_client/cli.py
dpd_client/client.py
dpd_client/errors.py
dpd_client/http.py
dpd_client/models.py
dpd_client/params.py
dpd_client/py.typed
dpd_client-0.2.0.dist-info/METADATA
dpd_client-0.2.0.dist-info/WHEEL
dpd_client-0.2.0.dist-info/entry_points.txt
dpd_client-0.2.0.dist-info/licenses/LICENSE
dpd_client-0.2.0.dist-info/RECORD
