Metadata-Version: 2.4
Name: dpd-client
Version: 0.2.0
Summary: Python client and CLI for Health Canada Drug Product Database (DPD) API
Author-email: tlow22 <thaddeuslow@outlook.com>
License-File: LICENSE
Requires-Python: >=3.9
Requires-Dist: httpx>=0.28.1
Requires-Dist: pydantic>=2.11.9
Requires-Dist: rich>=14.1.0
Requires-Dist: tenacity>=9.1.2
Requires-Dist: typer>=0.17.4
